fusionsolar/__init__.py
fusionsolar/client.py
testkerrsidnetfusion-0.0.6.dist-info/LICENSE
testkerrsidnetfusion-0.0.6.dist-info/METADATA
testkerrsidnetfusion-0.0.6.dist-info/WHEEL
testkerrsidnetfusion-0.0.6.dist-info/top_level.txt
testkerrsidnetfusion-0.0.6.dist-info/RECORD
