Metadata-Version: 2.1
Name: testkerrsidnetfusion
Version: 0.0.6
Summary: A Python client for Huawei FusionSolar
Home-page: UNKNOWN
License: UNKNOWN
Keywords: Huawei PV Solar FusionSolar API Python
Platform: UNKNOWN
Classifier: Development Status :: 3 - Alpha
Classifier: Intended Audience :: Developers
Classifier: Topic :: Scientific/Engineering
Classifier: License :: OSI Approved :: MIT License
Classifier: Programming Language :: Python :: 3.6
Classifier: Programming Language :: Python :: 3.7
License-File: LICENSE
Requires-Dist: requests
Requires-Dist: pandas
